{"name":"build-javascript","namedChunkGroups":{"app":{"name":"app","assets":[{"name":"webpack-runtime-bd304b6b5652f9728fff.js","size":3858},{"name":"styles.cf0fcbede1a63147c9fe.css","size":114577},{"name":"framework-253d5dbcb43c86ef3839.js","size":140783},{"name":"app-226beb1eb8865c1285d5.js","size":298245}],"filteredAssets":0,"assetsSize":557463,"filteredAuxiliaryAssets":8,"auxiliaryAssetsSize":2508207},"component---src-pages-404-js":{"name":"component---src-pages-404-js","assets":[{"name":"styles.cf0fcbede1a63147c9fe.css","size":114577},{"name":"commons-2e364ca2cadff0305b15.js","size":84850},{"name":"component---src-pages-404-js-c387d86d54a3beb44f8b.js","size":992}],"filteredAssets":0,"assetsSize":200419,"filteredAuxiliaryAssets":8,"auxiliaryAssetsSize":1109953},"component---src-pages-index-js":{"name":"component---src-pages-index-js","assets":[{"name":"styles.cf0fcbede1a63147c9fe.css","size":114577},{"name":"commons-2e364ca2cadff0305b15.js","size":84850},{"name":"component---src-pages-index-js-8a625b802342c48cf2bc.js","size":1612}],"filteredAssets":0,"assetsSize":201039,"filteredAuxiliaryAssets":9,"auxiliaryAssetsSize":3848732}},"assetsByChunkName":{"app":["webpack-runtime-bd304b6b5652f9728fff.js","styles.cf0fcbede1a63147c9fe.css","framework-253d5dbcb43c86ef3839.js","app-226beb1eb8865c1285d5.js"],"component---src-pages-404-js":["styles.cf0fcbede1a63147c9fe.css","commons-2e364ca2cadff0305b15.js","component---src-pages-404-js-c387d86d54a3beb44f8b.js"],"component---src-pages-index-js":["styles.cf0fcbede1a63147c9fe.css","commons-2e364ca2cadff0305b15.js","component---src-pages-index-js-8a625b802342c48cf2bc.js"]},"childAssetsByChunkName":{}}